calipy/__init__.py
calipy/base.py
calipy/components.py
calipy/constraints.py
calipy/data.py
calipy/effects.py
calipy/funs.py
calipy/illustrator.py
calipy/instruments.py
calipy/optimizer.py
calipy/primitives.py
calipy/tensor.py
calipy/utils.py
calipy/dist/__init__.py
calipy/dist/distributions.py
calipy/library/calipy_component_library.py
calipy/library/calipy_effects_library.py
calipy/library/calipy_instruments_library.py
calipy_ppl-0.5.2.dist-info/LICENSE.md
calipy_ppl-0.5.2.dist-info/METADATA
calipy_ppl-0.5.2.dist-info/WHEEL
calipy_ppl-0.5.2.dist-info/top_level.txt
calipy_ppl-0.5.2.dist-info/RECORD
