Metadata-Version: 2.1
Name: calipy-ppl
Version: 0.5.2
Summary: CaliPy (Calibration library Python) is a modular library for building and solving probabilistic models of measurement devices. Designed for scientific calibration tasks and uncertainty quantification.
Author-email: "Dr. Jemil Avers Butt" <jemil.butt@atlasoptimization.com>
License: Prosperity Public License
Project-URL: Homepage, http://github.com/atlasoptimization/calipy
Project-URL: Documentation, https://atlasoptimization.github.io/calipy
Project-URL: Source, http://github.com/atlasoptimization/calipy
Project-URL: Issues, http://github.com/atlasoptimization/calipy/issues
Project-URL: Changelog, https://github.com/atlasoptimization/calipy/releases
Keywords: instrument calibration,measurement devices,probabilistic modeling,bayesian inference,uncertainty quantification,pyro,pytorch
Classifier: Development Status :: 2 - Pre-Alpha
Classifier: Intended Audience :: Science/Research
Classifier: Topic :: Scientific/Engineering
Classifier: Topic :: Scientific/Engineering :: Mathematics
Classifier: Topic :: Scientific/Engineering :: Physics
Classifier: License :: Other/Proprietary License
Classifier: Programming Language :: Python :: 3
Classifier: Programming Language :: Python :: 3.7
Classifier: Programming Language :: Python :: 3.8
Classifier: Programming Language :: Python :: 3.9
Classifier: Programming Language :: Python :: 3.10
Requires-Python: >=3.7
License-File: LICENSE.md
Requires-Dist: torch>=2.0
Requires-Dist: pyro-ppl>=1.8.6
Requires-Dist: pandas>=2.0.0
Requires-Dist: matplotlib>=3.3.0
Requires-Dist: einops>=0.8.1
Requires-Dist: torchviz>=0.0.2
Requires-Dist: varname>=0.8.1
Requires-Dist: networkx>=2.4
Provides-Extra: dev
Requires-Dist: pytest>=3.7; extra == "dev"
